polychase_core.cp311-win_amd64.pyd
tbb12.dll
polychase_core-0.0.3.dist-info/METADATA
polychase_core-0.0.3.dist-info/WHEEL
polychase_core-0.0.3.dist-info/licenses/COPYING
polychase_core-0.0.3.dist-info/RECORD
