Metadata-Version: 2.4
Name: polychase_core
Version: 0.0.3
Summary: Polychase motion tracking core bindings
Author-Email: Ahmed Essam <aessam.dahy@gmail.com>
License-Expression: GPL-3.0-or-later
License-File: COPYING
Project-URL: Homepage, https://github.com/theartful/polychase
Project-URL: Issues, https://github.com/theartful/polychase/issues
Requires-Python: ==3.11
